LICENSE
MANIFEST.in
README.md
dev_requirements.txt
requirements.txt
setup.cfg
setup.py
versioneer.py
csirtg_hunter/__init__.py
csirtg_hunter/_version.py
csirtg_hunter/constants.py
csirtg_hunter/utils.py
csirtg_hunter.egg-info/PKG-INFO
csirtg_hunter.egg-info/SOURCES.txt
csirtg_hunter.egg-info/dependency_links.txt
csirtg_hunter.egg-info/entry_points.txt
csirtg_hunter.egg-info/requires.txt
csirtg_hunter.egg-info/top_level.txt
csirtg_hunter/plugins/__init__.py
csirtg_hunter/plugins/csirtg.py
csirtg_hunter/plugins/farsight.py
csirtg_hunter/plugins/fqdn.py
csirtg_hunter/plugins/fqdn_subdomain.py
csirtg_hunter/plugins/ipv4_resolve_prefix_whitelist.py
csirtg_hunter/plugins/spamhaus.py
csirtg_hunter/plugins/url.py
test/test_basics.py