Metadata-Version: 1.1
Name: csirtg-hunter
Version: 2.0b1
Summary: CSIRTG Hunter Framework
Home-page: https://github.com/csirtgadgets/csirtg-hunter-py
Author: Wes Young
Author-email: wes@csirtgadgets.com
License: MPL2
Keywords: security
Platform: UNKNOWN
Classifier: Topic :: System :: Networking
Classifier: Programming Language :: Python
